README.txt
bootstrap.py
buildout.cfg
setup.py
docs/HISTORY.txt
docs/LICENSE.GPL
docs/LICENSE.LGPL
docs/LICENSE.txt
src/chaoflow/__init__.py
src/chaoflow.testing.crawler.egg-info/PKG-INFO
src/chaoflow.testing.crawler.egg-info/SOURCES.txt
src/chaoflow.testing.crawler.egg-info/dependency_links.txt
src/chaoflow.testing.crawler.egg-info/entry_points.txt
src/chaoflow.testing.crawler.egg-info/namespace_packages.txt
src/chaoflow.testing.crawler.egg-info/not-zip-safe
src/chaoflow.testing.crawler.egg-info/requires.txt
src/chaoflow.testing.crawler.egg-info/top_level.txt
src/chaoflow/testing/__init__.py
src/chaoflow/testing/crawler/README.txt
src/chaoflow/testing/crawler/__init__.py
src/chaoflow/testing/crawler/fail.py
src/chaoflow/testing/crawler/globs.py
src/chaoflow/testing/crawler/module.py
src/chaoflow/testing/crawler/not_searched.txt
src/chaoflow/testing/crawler/testing.py
src/chaoflow/testing/crawler/tests.py
src/chaoflow/testing/crawler/utils.py
src/chaoflow/testing/crawler/no_package/no_package_file.py
src/chaoflow/testing/crawler/no_package/no_package_file.txt
src/chaoflow/testing/crawler/no_package/no_package_file2.py
src/chaoflow/testing/crawler/no_package/no_package_file3.py
src/chaoflow/testing/crawler/package/__init__.py
src/chaoflow/testing/crawler/package/module.py
src/chaoflow/testing/crawler/package/module.txt
src/chaoflow/testing/crawler/package/not_searched.txt
src/chaoflow/testing/crawler/package/subpackage/__init__.py
src/chaoflow/testing/crawler/package/subpackage/module.py