Metadata-Version: 1.0
Name: chaoflow.testing.crawler
Version: 0.3
Summary: Recursively finds tests in your package
Home-page: http://github.com/chaoflow/chaoflow.testing.crawler
Author: Florian Friesdorf
Author-email: flo@chaoflow.net
License: LGPL
Platform: UNKNOWN
Classifier: Development Status :: 4 - Beta
Classifier: Intended Audience :: Developers
Classifier: Programming Language :: Python
Classifier: Natural Language :: English
Classifier: Operating System :: OS Independent
